hdf5array/Hdf5CompressedSparseMatrixSeed.py
hdf5array/Hdf5DenseArraySeed.py
hdf5array/__init__.py
hdf5array-0.5.0.dist-info/LICENSE.txt
hdf5array-0.5.0.dist-info/METADATA
hdf5array-0.5.0.dist-info/WHEEL
hdf5array-0.5.0.dist-info/top_level.txt
hdf5array-0.5.0.dist-info/RECORD
