Metadata-Version: 2.1
Name: hdf5array
Version: 0.5.0
Summary: HDF5-backed objects for array and matrix like data
Home-page: https://github.com/biocpy/hdf5array
Author: Jayaram Kancherla
Author-email: jayaram.kancherla@gmail.com
License: MIT
Project-URL: Documentation, https://biocpy.github.io/hdf5array/
Platform: any
Classifier: Development Status :: 4 - Beta
Classifier: Programming Language :: Python
Requires-Python: >=3.9
License-File: LICENSE.txt
Requires-Dist: importlib-metadata; python_version < "3.8"
Requires-Dist: delayedarray>=0.5.0
Requires-Dist: numpy
Requires-Dist: h5py
Provides-Extra: testing
Requires-Dist: setuptools; extra == "testing"
Requires-Dist: pytest; extra == "testing"
Requires-Dist: pytest-cov; extra == "testing"
Requires-Dist: scipy; extra == "testing"
